{
  "version": "1.0",
  "pipeline": "COMPLETE",
  "phases": {
    "DECOMPOSE": {
      "status": "complete",
      "attempts": 0,
      "error": null,
      "completedAt": "2026-03-01T04:37:48.876Z"
    },
    "RESEARCH": {
      "status": "complete",
      "attempts": 0,
      "error": null,
      "completedAt": "2026-03-01T06:17:32.241Z"
    },
    "SYNTHESIZE": {
      "status": "complete",
      "attempts": 0,
      "error": null,
      "completedAt": "2026-03-01T06:21:36.747Z"
    },
    "CONTENT": {
      "status": "complete",
      "attempts": 0,
      "error": null,
      "completedAt": "2026-03-01T16:17:14.240Z"
    },
    "TTS": {
      "status": "complete",
      "attempts": 0,
      "error": null,
      "completedAt": "2026-03-01T17:07:07.092Z"
    },
    "DEPOSIT": {
      "status": "complete",
      "attempts": 0,
      "error": null,
      "completedAt": "2026-03-01T17:17:12.558Z"
    },
    "VALIDATE": {
      "status": "pending",
      "attempts": 0,
      "error": null,
      "completedAt": null
    }
  },
  "topicCount": 0,
  "startedAt": "2026-03-01T04:35:31.273Z",
  "updatedAt": "2026-03-01T17:21:11.179Z"
}